odoo/addons/account_invoice_ubl_peppol/README.rst
odoo/addons/account_invoice_ubl_peppol/__init__.py
odoo/addons/account_invoice_ubl_peppol/__manifest__.py
odoo/addons/account_invoice_ubl_peppol/data/peppol.eas.list.csv
odoo/addons/account_invoice_ubl_peppol/i18n/account_invoice_ubl_email_attachment.pot
odoo/addons/account_invoice_ubl_peppol/i18n/account_invoice_ubl_peppol.pot
odoo/addons/account_invoice_ubl_peppol/i18n/de.po
odoo/addons/account_invoice_ubl_peppol/i18n/hr.po
odoo/addons/account_invoice_ubl_peppol/i18n/nl.po
odoo/addons/account_invoice_ubl_peppol/models/__init__.py
odoo/addons/account_invoice_ubl_peppol/models/account_move.py
odoo/addons/account_invoice_ubl_peppol/models/peppol_eas_list.py
odoo/addons/account_invoice_ubl_peppol/models/res_company.py
odoo/addons/account_invoice_ubl_peppol/models/res_config_settings.py
odoo/addons/account_invoice_ubl_peppol/models/res_country.py
odoo/addons/account_invoice_ubl_peppol/models/res_partner.py
odoo/addons/account_invoice_ubl_peppol/readme/CONFIGURE.rst
odoo/addons/account_invoice_ubl_peppol/readme/CONTRIBUTORS.rst
odoo/addons/account_invoice_ubl_peppol/readme/DESCRIPTION.rst
odoo/addons/account_invoice_ubl_peppol/readme/ROADMAP.rst
odoo/addons/account_invoice_ubl_peppol/readme/USAGE.rst
odoo/addons/account_invoice_ubl_peppol/security/ir.model.access.csv
odoo/addons/account_invoice_ubl_peppol/static/description/icon.png
odoo/addons/account_invoice_ubl_peppol/static/description/index.html
odoo/addons/account_invoice_ubl_peppol/tests/__init__.py
odoo/addons/account_invoice_ubl_peppol/tests/test_ubl_email_attachment.py
odoo/addons/account_invoice_ubl_peppol/views/peppol_eas_list.xml
odoo/addons/account_invoice_ubl_peppol/views/res_config_settings.xml
odoo/addons/account_invoice_ubl_peppol/views/res_country.xml
odoo13_addon_account_invoice_ubl_peppol-13.0.1.1.0.dist-info/METADATA
odoo13_addon_account_invoice_ubl_peppol-13.0.1.1.0.dist-info/WHEEL
odoo13_addon_account_invoice_ubl_peppol-13.0.1.1.0.dist-info/top_level.txt
odoo13_addon_account_invoice_ubl_peppol-13.0.1.1.0.dist-info/RECORD
