Metadata-Version: 2.1
Name: odoo13-addon-account-invoice-ubl-peppol
Version: 13.0.1.1.0
Summary: Generate invoices in PEPPOL 3.0 BIS dialect
Home-page: https://github.com/OCA/edi
Author: Sunflower IT, Odoo Community Association (OCA)
Author-email: support@odoo-community.org
License: AGPL-3
Platform: UNKNOWN
Classifier: Programming Language :: Python
Classifier: Framework :: Odoo
Classifier: Framework :: Odoo :: 13.0
Classifier: License :: OSI Approved :: GNU Affero General Public License v3
Requires-Python: >=3.5
Requires-Dist: odoo13-addon-account-invoice-ubl
Requires-Dist: odoo13-addon-partner-coc
Requires-Dist: odoo (<13.1dev,>=13.0a)
